setup.py
mongoengine_extras/__init__.py
mongoengine_extras/fields.py
mongoengine_extras/utils.py
mongoengine_extras.egg-info/PKG-INFO
mongoengine_extras.egg-info/SOURCES.txt
mongoengine_extras.egg-info/dependency_links.txt
mongoengine_extras.egg-info/requires.txt
mongoengine_extras.egg-info/top_level.txt
tests/__init__.py