Metadata-Version: 1.0
Name: mongoengine-extras
Version: 0.0.1
Summary: Extra fields and utilities for mongoengine.
Home-page: https://github.com/bennylope/mongoengine-extras
Author: Ben Lopatin
Author-email: ben.lopatin@wellfireinteractive.com
License: Public Domain
Platform: any
Classifier: Development Status :: 3 - Alpha
Classifier: Intended Audience :: Developers
Classifier: License :: Public Domain
Classifier: Operating System :: OS Independent
Classifier: Programming Language :: Python
Classifier: Topic :: Database
Classifier: Topic :: Software Development :: Libraries :: Python Modules
